<?xml version="1.0" encoding="utf-8" ?>
<dwsync>
<file name="activitySuccess.php" server="sgws11.hospedagemdesites.ws" local="130475202946497438" remote="130475798400000000" Dst="1" />
<file name="analisisCriticoSuccess.php" server="sgws11.hospedagemdesites.ws" local="130475202966500885" remote="130475798400000000" Dst="1" />
<file name="createAnalisisSuccess.php" server="sgws11.hospedagemdesites.ws" local="130475202976377414" remote="130475798400000000" Dst="1" />
<file name="editAnalisisCriticoSuccess.php" server="sgws11.hospedagemdesites.ws" local="130475202971804401" remote="130475798400000000" Dst="1" />
<file name="editAnexoSuccess.php" server="sgws11.hospedagemdesites.ws" local="130475202937995096" remote="130475798400000000" Dst="1" />
<file name="editSuccess.php" server="sgws11.hospedagemdesites.ws" local="130475202956991386" remote="130475798400000000" Dst="1" />
<file name="indexSuccess.php" server="sgws11.hospedagemdesites.ws" local="130475202962464048" remote="130475798400000000" Dst="1" />
<file name="listaAnalisisSuccess.php" server="sgws11.hospedagemdesites.ws" local="130475202952638493" remote="130475798400000000" Dst="1" />
<file name="newSuccess.php" server="sgws11.hospedagemdesites.ws" local="130475202949312681" remote="130475798400000000" Dst="1" />
<file name="_form.php" server="sgws11.hospedagemdesites.ws" local="130475202942624899" remote="130475798400000000" Dst="1" />
</dwsync>